falgueras/__init__.py
falgueras/common/__init__.py
falgueras/common/datetime_utils.py
falgueras/common/enums.py
falgueras/common/json_utils.py
falgueras/common/logging_utils.py
falgueras/gcp/BqClient.py
falgueras/gcp/GcsClient.py
falgueras/gcp/GoogleDriveClient.py
falgueras/gcp/SecretManagerClient.py
falgueras/gcp/__init__.py
falgueras/gcp/services_toolbox.py
falgueras/gcp/natural_language/NaturalLanguageClient.py
falgueras/gcp/natural_language/__init__.py
falgueras/gcp/natural_language/model.py
falgueras/gcp/natural_language/natural_language_utils.py
falgueras/pandaas/PandasRepoFactory.py
falgueras/pandaas/__init__.py
falgueras/pandaas/pandas_repo.py
falgueras/pandaas/pandas_utils.py
falgueras/spark/BqSparkSchema.py
falgueras/spark/__init__.py
falgueras/spark/dataframe_utils.py
falgueras/spark/spark_session_utils.py
falgueras/spark/repo/SparkRepoFactory.py
falgueras/spark/repo/__init__.py
falgueras/spark/repo/spark_repo.py
falgueras-1.1.6.dist-info/METADATA
falgueras-1.1.6.dist-info/WHEEL
falgueras-1.1.6.dist-info/licenses/LICENSE
falgueras-1.1.6.dist-info/RECORD
