Metadata-Version: 2.4
Name: falgueras
Version: 1.1.6
Summary: Common code for Python projects involving GCP, Pandas, and Spark.
Author-email: Aleix Falgueras Casals <falguerasaleix@gmail.com>
License: MIT
License-File: LICENSE
Classifier: License :: OSI Approved :: MIT License
Classifier: Operating System :: OS Independent
Classifier: Programming Language :: Python :: 3
Requires-Python: >=3.10
Requires-Dist: colorama~=0.4.6
Requires-Dist: db-dtypes~=1.3.1
Requires-Dist: google-api-core~=2.24.0
Requires-Dist: google-api-python-client~=2.156.0
Requires-Dist: google-auth~=2.37.0
Requires-Dist: google-cloud-bigquery-storage~=2.27.0
Requires-Dist: google-cloud-bigquery~=3.27.0
Requires-Dist: google-cloud-language~=2.16.0
Requires-Dist: google-cloud-secret-manager~=2.22.0
Requires-Dist: google-cloud-storage~=2.19.0
Requires-Dist: google-cloud-translate~=3.20.1
Requires-Dist: numpy==1.26.4
Requires-Dist: pandas==2.1.4
Requires-Dist: protobuf~=5.29.2
Requires-Dist: pytz~=2024.2
Requires-Dist: requests~=2.32.3
Provides-Extra: spark
Requires-Dist: findspark==1.4.2; extra == 'spark'
Requires-Dist: pyarrow==12.0.1; extra == 'spark'
Requires-Dist: pyspark==3.5.2; extra == 'spark'
